fastapi_authorization_gateway/__init__.py
fastapi_authorization_gateway/auth.py
fastapi_authorization_gateway/helpers.py
fastapi_authorization_gateway/permissions.py
fastapi_authorization_gateway/search.py
fastapi_authorization_gateway/types.py
fastapi_authorization_gateway/utils.py
fastapi_authorization_gateway-0.0.4.dist-info/METADATA
fastapi_authorization_gateway-0.0.4.dist-info/WHEEL
fastapi_authorization_gateway-0.0.4.dist-info/licenses/LICENSE
fastapi_authorization_gateway-0.0.4.dist-info/RECORD
