Metadata-Version: 2.3
Name: fastapi-authorization-gateway
Version: 0.0.4
Summary: A route-based authorization framework for FastAPI
Project-URL: Homepage, https://github.com/developmentseed/fastapi-authorization-gateway
Project-URL: Source, https://github.com/developmentseed/fastapi-authorization-gateway
Author-email: Edward Keeble <ed@developmentseed.org>, Anthony Lukach <anthony@developmentseed.org>, Vincent Sarago <vincent@developmentseed.org>
License: MIT License
License-File: LICENSE
Keywords: Authorization,FastAPI
Classifier: Intended Audience :: Information Technology
Classifier: Intended Audience :: Science/Research
Classifier: License :: OSI Approved :: BSD License
Classifier: Programming Language :: Python :: 3.8
Classifier: Programming Language :: Python :: 3.9
Classifier: Programming Language :: Python :: 3.10
Classifier: Programming Language :: Python :: 3.11
Classifier: Programming Language :: Python :: 3.12
Requires-Python: >=3.8
Requires-Dist: fastapi-slim>=0.111.0
Requires-Dist: typing-extensions; python_version < '3.9'
Provides-Extra: dev
Requires-Dist: pre-commit; extra == 'dev'
Provides-Extra: test
Requires-Dist: httpx; extra == 'test'
Requires-Dist: pytest; extra == 'test'
Requires-Dist: pytest-cov; extra == 'test'
